{
	"name": "PL_filter",
	"properties": {
		"activities": [
			{
				"name": "Filter1",
				"type": "Filter",
				"dependsOn": [],
				"userProperties": [],
				"typeProperties": {
					"items": {
						"value": "@pipeline().parameters.var",
						"type": "Expression"
					},
					"condition": {
						"value": "@greater(item(),2)",
						"type": "Expression"
					}
				}
			},
			{
				"name": "Set variable1",
				"type": "SetVariable",
				"dependsOn": [
					{
						"activity": "Filter1",
						"dependencyConditions": [
							"Succeeded"
						]
					}
				],
				"policy": {
					"secureOutput": false,
					"secureInput": false
				},
				"userProperties": [],
				"typeProperties": {
					"variableName": "varint",
					"value": {
						"value": "@activity('Filter1').output.FilteredItemsCount",
						"type": "Expression"
					}
				}
			},
			{
				"name": "Set variable2",
				"type": "SetVariable",
				"dependsOn": [
					{
						"activity": "Filter1",
						"dependencyConditions": [
							"Succeeded"
						]
					}
				],
				"policy": {
					"secureOutput": false,
					"secureInput": false
				},
				"userProperties": [],
				"typeProperties": {
					"variableName": "varint1",
					"value": {
						"value": "@activity('Filter1').output.ItemsCount",
						"type": "Expression"
					}
				}
			},
			{
				"name": "Set variable3",
				"type": "SetVariable",
				"dependsOn": [
					{
						"activity": "Filter1",
						"dependencyConditions": [
							"Succeeded"
						]
					}
				],
				"policy": {
					"secureOutput": false,
					"secureInput": false
				},
				"userProperties": [],
				"typeProperties": {
					"variableName": "varint2",
					"value": {
						"value": "@activity('Filter1').output.Value[2]",
						"type": "Expression"
					}
				}
			}
		],
		"parameters": {
			"var": {
				"type": "array",
				"defaultValue": [
					1,
					2,
					3,
					4,
					5
				]
			}
		},
		"variables": {
			"varint": {
				"type": "Integer"
			},
			"varint1": {
				"type": "Integer"
			},
			"varint2": {
				"type": "Integer"
			}
		},
		"annotations": [],
		"lastPublishTime": "2025-11-04T02:54:31Z"
	},
	"type": "Microsoft.DataFactory/factories/pipelines"
}